lazyllm/__init__.py
lazyllm/cli/README.md
lazyllm/cli/__init__.py
lazyllm/cli/deploy.py
lazyllm/cli/install.py
lazyllm/cli/main.py
lazyllm/cli/run.py
lazyllm/common/__init__.py
lazyllm/common/bind.py
lazyllm/common/common.py
lazyllm/common/deprecated.py
lazyllm/common/exception.py
lazyllm/common/globals.py
lazyllm/common/inspection.py
lazyllm/common/logger/__init__.py
lazyllm/common/logger/logger.py
lazyllm/common/multiprocessing.py
lazyllm/common/option.py
lazyllm/common/queue.py
lazyllm/common/redis_client.py
lazyllm/common/registry.py
lazyllm/common/text.py
lazyllm/common/threading.py
lazyllm/common/utils.py
lazyllm/components/__init__.py
lazyllm/components/auto/__init__.py
lazyllm/components/auto/auto_helper.py
lazyllm/components/auto/autodeploy.py
lazyllm/components/auto/autofinetune.py
lazyllm/components/auto/dependencies/__init__.py
lazyllm/components/auto/dependencies/modelsconfig.py
lazyllm/components/auto/dependencies/requirements.py
lazyllm/components/core.py
lazyllm/components/data.py
lazyllm/components/deploy/__init__.py
lazyllm/components/deploy/base.py
lazyllm/components/deploy/embed.py
lazyllm/components/deploy/graphrag/__init__.py
lazyllm/components/deploy/infinity.py
lazyllm/components/deploy/lightllm.py
lazyllm/components/deploy/lmdeploy/chat_template.json
lazyllm/components/deploy/lmdeploy.py
lazyllm/components/deploy/mindie/config.json
lazyllm/components/deploy/mindie.py
lazyllm/components/deploy/ocr/__init__.py
lazyllm/components/deploy/ocr/pp_ocr.py
lazyllm/components/deploy/ray.py
lazyllm/components/deploy/relay/__init__.py
lazyllm/components/deploy/relay/base.py
lazyllm/components/deploy/relay/server.py
lazyllm/components/deploy/speech_to_text/__init__.py
lazyllm/components/deploy/speech_to_text/sense_voice.py
lazyllm/components/deploy/stable_diffusion/__init__.py
lazyllm/components/deploy/stable_diffusion/stable_diffusion3.py
lazyllm/components/deploy/text_to_speech/__init__.py
lazyllm/components/deploy/text_to_speech/bark.py
lazyllm-0.7.4.dist-info/METADATA
lazyllm-0.7.4.dist-info/WHEEL
lazyllm-0.7.4.dist-info/entry_points.txt
lazyllm-0.7.4.dist-info/licenses/NOTICE
lazyllm-0.7.4.dist-info/licenses/LICENSE
lazyllm-0.7.4.dist-info/RECORD
