Metadata-Version: 2.4
Name: lazyllm
Version: 0.7.4
Summary: A Low-code Development Tool For Building Multi-agent LLMs Applications.
Author-Email: wangzhihong <wangzhihong@sensetime.com>
License-Expression: Apache-2.0
Requires-Python: <3.14,>=3.10
Requires-Dist: toml
Requires-Dist: tqdm
Requires-Dist: filelock
Requires-Dist: pyyaml
Requires-Dist: packaging
Requires-Dist: fastapi>=0.111.0
Requires-Dist: loguru>=0.7.2
Requires-Dist: pydantic<3.0.0,>=2.11.7
Requires-Dist: requests>=2.32.2
Requires-Dist: uvicorn>=0.23.2
Requires-Dist: cloudpickle>=3.0.0
Requires-Dist: docstring-parser<0.17,>=0.16
Requires-Dist: json5<0.10.0,>=0.9.25
Requires-Dist: pyjwt>=2.8.0
Requires-Dist: psutil<7.0.0,>=6.0.0
Requires-Dist: deepdiff>=8.6.1
